granting/__init__.py
granting/main.py
granting/send_data.py
GrantingUNOB-0.0.1.dist-info/LICENSE
GrantingUNOB-0.0.1.dist-info/METADATA
GrantingUNOB-0.0.1.dist-info/WHEEL
GrantingUNOB-0.0.1.dist-info/top_level.txt
GrantingUNOB-0.0.1.dist-info/RECORD
