Metadata-Version: 2.1
Name: GrantingUNOB
Version: 0.0.1
Summary: A package for extracting and processing Cyber Security program data
Home-page: https://github.com/Hieuducemo/Granting-database
Author: Tran Hieu Duc, To Minh Quan
Author-email: heovip1ad@gmail.com
Classifier: Programming Language :: Python :: 3
Classifier: License :: OSI Approved :: MIT License
Classifier: Operating System :: OS Independent
Requires-Python: >=3.6
License-File: LICENSE
Requires-Dist: beautifulsoup4
Requires-Dist: selenium
Requires-Dist: webdriver-manager
